<?xml version="1.0" encoding="ISO-8859-1"?>
<Configuracion>
   <Process>2</Process>
    <Path/>
    <DbConn>
        <Adapter>PostgreSqlPdo</Adapter>
        <Server>localhost</Server>
        <Port>5432</Port>
        <Database>sstuv_app</Database>
        <Username>postgres</Username>
        <Password>password</Password>
        <Profiling>false</Profiling>
        <Inicializada>1</Inicializada>
    </DbConn>
   <DbConnProc>
        <Adapter>PostgreSqlPdo</Adapter>
        <Server>localhost</Server>
        <Port>5432</Port>
        <Database>cenpeproc</Database>
        <Username>redfie</Username>
        <Password>redfie11</Password>
        <Profiling>false</Profiling>
        <Inicializada>1</Inicializada>
    </DbConnProc>
    <ServerInstance/>
    <Email>
        <Enabled>false</Enabled>
        <Smtp></Smtp>
        <From></From>
        <To/>
        <UserName></UserName>
        <UserPassword></UserPassword>
        <Port>25</Port>
        <AuthPlain>false</AuthPlain>
        <AuthLogin>true</AuthLogin>
    </Email>
    <WebServicePadron>
        <Uri></Uri>
        <!--Uri>localhost/padron/WebService.php</Uri-->
    </WebServicePadron>
    <AuthMe>
        <AuthmeUri/>
        <UseAuthMe>false</UseAuthMe>
        <AdminEmail/>
    </AuthMe>
<FechaUltimaArticulacion>2014-09-23 21:04:33</FechaUltimaArticulacion>
</Configuracion>
